pyGenicParser/__init__.py
pyGenicParser/bgenObject.py
pyGenicParser/errors_codes.py
pyGenicParser/misc.py
pyGenicParser/plinkObject.py
pyGenicParser/variantObjects.py
pyGenicParser/Tests/UnitTests.py
pyGenicParser/Tests/__init__.py
pyGenicParser/Tests/Data/EUR.ldpred_21.bed
pyGenicParser/Tests/Data/EUR.ldpred_21.bgen
pyGenicParser/Tests/Data/EUR.ldpred_21.bgen.bgi
pyGenicParser/Tests/Data/EUR.ldpred_21.bim
pyGenicParser/Tests/Data/EUR.ldpred_21.bim.bgi
pyGenicParser/Tests/Data/EUR.ldpred_21.fam
pyGenicParser/Tests/Data/Write/write.txt
pyGenicParser-0.4.0.dist-info/LICENSE
pyGenicParser-0.4.0.dist-info/METADATA
pyGenicParser-0.4.0.dist-info/WHEEL
pyGenicParser-0.4.0.dist-info/top_level.txt
pyGenicParser-0.4.0.dist-info/RECORD
